pymiscell/__init__.py
pymiscell/databases_tools.py
pymiscell/filesystem_tools.py
pymiscell/internet_tools.py
pymiscell/math_tools.py
pymiscell/plot_tools.py
pymiscell/statistics_tools.py
pymiscell/strings_tools.py
pymiscell/to_do.py
pymiscell/try_r_python.py
pymiscell-0.0.1.dist-info/LICENSE
pymiscell-0.0.1.dist-info/METADATA
pymiscell-0.0.1.dist-info/WHEEL
pymiscell-0.0.1.dist-info/top_level.txt
pymiscell-0.0.1.dist-info/RECORD
