Metadata-Version: 2.1
Name: pymiscell
Version: 0.0.1
Summary: A package with miscellaneous, common use tools
Home-page: https://github.com/rodrigo1392/pymiscell
Author: Rodrigo Rivero
Author-email: rodrigo.m.rivero13@gmail.com
License: UNKNOWN
Platform: UNKNOWN
Classifier: Programming Language :: Python :: 3
Classifier: License :: OSI Approved :: MIT License
Classifier: Operating System :: OS Independent
Requires-Python: >=3.6
Requires-Dist: h5py
Requires-Dist: IPython
Requires-Dist: matplotlib
Requires-Dist: numpy
Requires-Dist: pandas
Requires-Dist: pytest
Requires-Dist: rpy2
Requires-Dist: scipy
Requires-Dist: sympy
Requires-Dist: tqdm
